[
  {
    "media": "El Confidencial",
    "title": "Ferraz tiene dosieres para implicar a PP y Manos Limpias en un complot contra el PSOE andaluz",
    "mediaUrl": "https://www.elconfidencial.com/"
  },
  {
    "media": "El País",
    "title": "World in Progress: un foro para entender y mejorar un mundo en cambio abrupto",
    "mediaUrl": "https://elpais.com/?ed=es"
  },
  {
    "media": "Público",
    "title": "El clamor contra el precio de la vivienda traslada la presión a unas instituciones incapaces de dar soluciones",
    "mediaUrl": "https://www.publico.es/"
  },
  {
    "media": "El Diario",
    "title": "La Xunta de Galicia entregó 782.666 euros en 272 contratos a dedo al hermano de la mano derecha de Alfonso Rueda",
    "mediaUrl": "https://www.eldiario.es/"
  },
  {
    "media": "Infolibre",
    "title": "El negocio de las grandes farmacéuticas",
    "mediaUrl": "https://www.infolibre.es/"
  },
  {
    "media": "La Vanguardia",
    "title": "Hizbulah golpea a Israel con drones y deja al menos cuatro muertos y más de 60 heridos",
    "mediaUrl": "https://www.lavanguardia.com"
  },
  {
    "media": "El Mundo",
    "title": "El embajador de Zapatero en Venezuela confiesa que cobró de la petrolera PDVSA asesorías ficticias millonarias",
    "mediaUrl": "https://elmundo.es"
  },
  {
    "media": "El Español",
    "title": "Aldama blanqueaba el dinero 'dejándolo dormir' unas horas en sociedades pantalla que creaba en Elvas",
    "mediaUrl": "https://elespanol.com"
  },
  {
    "media": "OK Diario",
    "title": "La 'clarividencia' de Juan Carlos I sobre Aznar poco antes de que ganara las elecciones: \"Éste no tiene tirón\"",
    "mediaUrl": "https://okdiario.com"
  },
  {
    "media": "20 minutos",
    "title": "La vivienda, casi inaccesible para los jóvenes: alquileres que 'se comen' más de la mitad del sueldo y pisos compartidos a los 30",
    "mediaUrl": "https://20minutos.es/"
  },
  {
    "media": "La Razón",
    "title": "Los peones de Sánchez se lanzan a controlar el postsanchismo",
    "mediaUrl": "https://www.larazon.es/"
  },
  {
    "media": "ABC",
    "title": "Junts exige que Cataluña cobre los millones no ejecutados en inversiones",
    "mediaUrl": "https://www.abc.es/"
  }
]