[
  {
    "media": "El Confidencial",
    "title": "Koldo repartía las mascarillas en Barajas sin control y Transportes aún almacena 440.000",
    "mediaUrl": "https://www.elconfidencial.com/"
  },
  {
    "media": "El País",
    "title": "Trump da la bienvenida a Kennedy Jr. a la familia MAGA",
    "mediaUrl": "https://elpais.com/?ed=es"
  },
  {
    "media": "Público",
    "title": "Sánchez afronta el inicio del curso político con dudas sobre los Presupuestos y frentes como Catalunya, el PP o el juez Peinado",
    "mediaUrl": "https://www.publico.es/"
  },
  {
    "media": "El Diario",
    "title": "Una ‘epidemia’ de silicosis azota España con 500 casos al año, la mitad de ellos por las encimeras de cuarzo",
    "mediaUrl": "https://www.eldiario.es/"
  },
  {
    "media": "Infolibre",
    "title": "El negocio de las grandes farmacéuticas",
    "mediaUrl": "https://www.infolibre.es/"
  },
  {
    "media": "La Vanguardia",
    "title": "Detenido un joven de 15 años por el ataque que dejó a tres muertos ayer en Alemania",
    "mediaUrl": "https://www.lavanguardia.com"
  },
  {
    "media": "El Mundo",
    "title": "El Gobierno reconoce ya la corrupción en el Ministerio de Ábalos en plena pandemia",
    "mediaUrl": "https://elmundo.es"
  },
  {
    "media": "El Español",
    "title": "\"Una respuesta simétrica a Rusia\": Zelenski alude a Kursk para celebrar el Día de la Independencia de Ucrania",
    "mediaUrl": "https://elespanol.com"
  },
  {
    "media": "OK Diario",
    "title": "Mónica García lanza una campaña que critica a los políticos que construyen hospitales",
    "mediaUrl": "https://okdiario.com"
  },
  {
    "media": "20 minutos",
    "title": "Los tres escenarios a los que se enfrenta el asesino de Mateo en Mocejón",
    "mediaUrl": "https://20minutos.es/"
  },
  {
    "media": "La Razón",
    "title": "Ábalos duplicó el pedido de mascarillas a la empresa de la trama en solo 38 minutos",
    "mediaUrl": "https://www.larazon.es/"
  },
  {
    "media": "ABC",
    "title": "Transportes tiene aún 1,2 millones de euros en mascarillas en el sótano del ministerio",
    "mediaUrl": "https://www.abc.es/"
  }
]