[
  {
    "media": "El Confidencial",
    "title": "Líbano eleva hasta 31 los fallecidos en el ataque del Ejércitoisraelí en Beirut",
    "mediaUrl": "https://www.elconfidencial.com/"
  },
  {
    "media": "El País",
    "title": "Más de 10 veces el presupuesto para migración y una posible recesión: el costo de la gran deportación de Trump",
    "mediaUrl": "https://elpais.com/?ed=es"
  },
  {
    "media": "Público",
    "title": "Defensa gasta en armas y otros materiales 746 millones, casi cuatro veces más que el bono anual para ayudas al alquiler joven",
    "mediaUrl": "https://www.publico.es/"
  },
  {
    "media": "El Diario",
    "title": "El PSOE se reúne con Junts en Suiza para reconstruir el acuerdo con Puigdemont",
    "mediaUrl": "https://www.eldiario.es/"
  },
  {
    "media": "Infolibre",
    "title": "El negocio de las grandes farmacéuticas",
    "mediaUrl": "https://www.infolibre.es/"
  },
  {
    "media": "La Vanguardia",
    "title": "Israel no da tregua a Hizbulah y descabeza su cúpula militar",
    "mediaUrl": "https://www.lavanguardia.com"
  },
  {
    "media": "El Mundo",
    "title": "Eudoro González, el hombre clave en la negociación para exiliar a Edmundo González por su conexión con Zapatero",
    "mediaUrl": "https://elmundo.es"
  },
  {
    "media": "El Español",
    "title": "Israel mata a Ibrahim 'el Eficiente' y venga 41 años después la masacre de 314 americanos en Beirut",
    "mediaUrl": "https://elespanol.com"
  },
  {
    "media": "OK Diario",
    "title": "Maduro prefirió Madrid a Miami para exiliar a Edmundo González: \"En España tiene espías para vigilarle\"",
    "mediaUrl": "https://okdiario.com"
  },
  {
    "media": "20 minutos",
    "title": "El PP ve en la última reunión del PSOE con Puigdemont \"la prueba de que el Gobierno está acabado\"",
    "mediaUrl": "https://20minutos.es/"
  },
  {
    "media": "La Razón",
    "title": "Feijóo ultima su \"ofensiva legislativa\" frente a Sánchez y se abre a negociar con Junts y PNV para desgastar al Gobierno",
    "mediaUrl": "https://www.larazon.es/"
  },
  {
    "media": "ABC",
    "title": "Edmundo González negoció con el chavismo a espaldas de la embajada holandesa antes de ir a la española",
    "mediaUrl": "https://www.abc.es/"
  }
]