[
  {
    "media": "El Confidencial",
    "title": "El 'DNI' de los nuevos españoles: jóvenes, latinos, formados y con mayor éxito laboral",
    "mediaUrl": "https://www.elconfidencial.com/"
  },
  {
    "media": "El País",
    "title": "Texas se enfrenta a una epidemia de amputaciones por la diabetes",
    "mediaUrl": "https://elpais.com/?ed=es"
  },
  {
    "media": "Público",
    "title": "Alquilar una habitación en España ya es un lujo: su precio se dispara un 42% en cinco años, hasta los 500 euros de media",
    "mediaUrl": "https://www.publico.es/"
  },
  {
    "media": "El Diario",
    "title": "Catalunya se encamina a un primer pleno de investidura que sirva solo como cuenta atrás electoral",
    "mediaUrl": "https://www.eldiario.es/"
  },
  {
    "media": "Infolibre",
    "title": "La Audiencia Nacional avala la batalla de Sanidad para impedir que se conozca el precio real de los fármacos",
    "mediaUrl": "https://www.infolibre.es/"
  },
  {
    "media": "La Vanguardia",
    "title": "Sánchez: “Hay que acabar con la impunidad de pseudomedios pagados por PP y Vox”",
    "mediaUrl": "https://www.lavanguardia.com"
  },
  {
    "media": "El Mundo",
    "title": "Los españoles aprueban a la Corona pero exigen más regeneración a Felipe VI tras 10 años de reinado",
    "mediaUrl": "https://elmundo.es"
  },
  {
    "media": "El Español",
    "title": "Felipe VI recupera el prestigio de la Corona con la mejor valoración en un cuarto de siglo",
    "mediaUrl": "https://elespanol.com"
  },
  {
    "media": "OK Diario",
    "title": "Sánchez se va a Suiza a \"defender\" la soberanía de Ucrania mientras da alas al separatismo en España",
    "mediaUrl": "https://okdiario.com"
  },
  {
    "media": "20 minutos",
    "title": "Sánchez y Milei coinciden por primera vez tras las crisis diplomática, pero se evitan en la cumbre sobre Ucrania",
    "mediaUrl": "https://20minutos.es/"
  },
  {
    "media": "La Razón",
    "title": "Alberto Núñez Feijóo: \"Sánchez engañó con la amnistía a Puigdemont\"",
    "mediaUrl": "https://www.larazon.es/"
  },
  {
    "media": "ABC",
    "title": "Felipe VI, el garante de la Constitución",
    "mediaUrl": "https://www.abc.es/"
  }
]