[
  {
    "media": "El Confidencial",
    "title": "Albares avisa a Israel tras el aumento de la tensión: \"Nadie nos va a amedrentar\"",
    "mediaUrl": "https://www.elconfidencial.com/"
  },
  {
    "media": "El País",
    "title": "Lo ‘cool’ es hablar spanglish, el ‘idioma’ que amenaza el anglocentrismo",
    "mediaUrl": "https://elpais.com/?ed=es"
  },
  {
    "media": "Público",
    "title": "Aumenta la escalada diplomática entre España e Israel a escasas horas del reconocimiento de Palestina",
    "mediaUrl": "https://www.publico.es/"
  },
  {
    "media": "El Diario",
    "title": "Decenas de muertos por un nuevo ataque israelí en un campo de refugiados en Rafah",
    "mediaUrl": "https://www.eldiario.es/"
  },
  {
    "media": "Infolibre",
    "title": "Conservadurismo, elitismo y desconexión: así marca el sistema de oposiciones a los jueces españoles",
    "mediaUrl": "https://www.infolibre.es/"
  },
  {
    "media": "La Vanguardia",
    "title": "Albares: “Nadie nos va a amedrentar en nuestra decisión de reconocer a Palestina”",
    "mediaUrl": "https://www.lavanguardia.com"
  },
  {
    "media": "El Mundo",
    "title": "El PP triunfará en las elecciones europeas con dos millones de votos de PSOE y Ciudadanos",
    "mediaUrl": "https://elmundo.es"
  },
  {
    "media": "El Español",
    "title": "Feijóo exige a Sánchez que retire la ley de amnistía y convoque ya elecciones: \"Ha engañado a todos\"",
    "mediaUrl": "https://elespanol.com"
  },
  {
    "media": "OK Diario",
    "title": "La diputada saharaui de Sumar llama a aniquilar Israel: \"La descolonización es un proceso violento\"",
    "mediaUrl": "https://okdiario.com"
  },
  {
    "media": "20 minutos",
    "title": "Feijóo pide a Sánchez retirar la amnistía y convocar elecciones generales: \"Tiene el país parado\"",
    "mediaUrl": "https://20minutos.es/"
  },
  {
    "media": "La Razón",
    "title": "Sánchez deberá responder sobre cómo ve la gobernabilidad de España en la próxima sesión de control",
    "mediaUrl": "https://www.larazon.es/"
  },
  {
    "media": "ABC",
    "title": "Un año de ley de Vivienda: casi 50.000 pisos menos en alquiler y un 10% más caros",
    "mediaUrl": "https://www.abc.es/"
  }
]